LICENSE
README.md
setup.cfg
setup.py
minichain/__init__.py
minichain/backend.py
minichain/base.py
minichain/gradio.py
minichain/push_to_hub.py
minichain.egg-info/PKG-INFO
minichain.egg-info/SOURCES.txt
minichain.egg-info/dependency_links.txt
minichain.egg-info/requires.txt
minichain.egg-info/top_level.txt
minichain/prompts/__init__.py
minichain/prompts/search.py
minichain/prompts/template.py
minichain/prompts/typed.py
minichain/templates/anthropic_hhh.tpl
minichain/templates/prompt.html.tpl
minichain/templates/self_instruct.tpl
minichain/templates/type_prompt.pmpt.tpl