Metadata-Version: 2.1
Name: minichain
Version: 0.3.3
Summary: A tiny library for large language models
Home-page: https://github.com/srush/minichain
Author: Sasha Rush
Author-email: srush.research@gmail.com
License: MIT
Project-URL: Documentation, https://srush.github.io/minichain
Project-URL: Source Code, https://github.com/srush/minichain
Project-URL: Issue Tracker, https://github.com/srush/minichain/issues
Platform: UNKNOWN
Classifier: Intended Audience :: Science/Research
Classifier: Operating System :: OS Independent
Classifier: Programming Language :: Python :: 3
Classifier: Programming Language :: Python :: 3.7
Classifier: Programming Language :: Python :: 3.8
Classifier: Programming Language :: Python :: 3.9
Classifier: License :: OSI Approved :: MIT License
Classifier: Topic :: Scientific/Engineering
License-File: LICENSE
